aoa/__init__.py
aoa/api_client.py
aoa/api/__init__.py
aoa/api/api_iterator.py
aoa/api/base_api.py
aoa/api/dataset_api.py
aoa/api/dataset_connection_api.py
aoa/api/dataset_template_api.py
aoa/api/deployment_api.py
aoa/api/iterator_base_api.py
aoa/api/job_api.py
aoa/api/job_event_api.py
aoa/api/message_api.py
aoa/api/model_api.py
aoa/api/project_api.py
aoa/api/trained_model_api.py
aoa/api/trained_model_artefacts_api.py
aoa/api/trained_model_event_api.py
aoa/cli/__init__.py
aoa/cli/base_model.py
aoa/cli/evaluate_model.py
aoa/cli/repo_manager.py
aoa/cli/run_model.R
aoa/cli/score_model.py
aoa/cli/train_model.py
aoa/cli/metadata_files/.gitignore
aoa/cli/metadata_files/readme.md
aoa/context/__init__.py
aoa/context/model_context.py
aoa/crypto/TJEncryptPassword.py
aoa/crypto/__init__.py
aoa/crypto/crypto.py
aoa/stats/__init__.py
aoa/stats/stats.py
aoa/stats/stats_util.py
aoa/stats/store.py
aoa/util/__init__.py
aoa/util/artifacts.py
aoa/util/byom.py
aoa/util/connections.py
aoa/util/sto.py
aoa-7.0.1.data/scripts/aoa
aoa-7.0.1.dist-info/LICENSE-3RD-PARTY.txt
aoa-7.0.1.dist-info/LICENSE.txt
aoa-7.0.1.dist-info/METADATA
aoa-7.0.1.dist-info/WHEEL
aoa-7.0.1.dist-info/top_level.txt
aoa-7.0.1.dist-info/RECORD
