Metadata-Version: 2.1
Name: aoa
Version: 7.0.1
Summary: Python client for Teradata AnalyticOps Accelerator (AOA)
Home-page: 
Author: Teradata
Author-email: teradata.corporation@teradatacorporation.com
Requires-Python: >=3.6
License-File: LICENSE.txt
License-File: LICENSE-3RD-PARTY.txt
Requires-Dist: jinja2 (==3.0.3)
Requires-Dist: requests (==2.27.1)
Requires-Dist: requests-oauthlib (==1.3.1)
Requires-Dist: aia (==0.1.0)
Requires-Dist: pyyaml (==5.3.1)
Requires-Dist: gitpython (==3.1.18)
Requires-Dist: cryptography (==3.4.8)
Requires-Dist: teradataml (>=17.0.0.4)
